setup.py
treant/__init__.py
treant.egg-info/PKG-INFO
treant.egg-info/SOURCES.txt
treant.egg-info/dependency_links.txt
treant.egg-info/top_level.txt