Metadata-Version: 1.0
Name: treant
Version: 0.4.0
Summary: Simple tree operations in Python
Home-page: https://github.com/framed-data/treant
Author: Elliot Block
Author-email: elliot@framed.io
License: UNKNOWN
Platform: UNKNOWN
